leap_model_parser/__init__.py
leap_model_parser/contract/__init__.py
leap_model_parser/contract/graph.py
leap_model_parser/contract/importmodelresponse.py
leap_model_parser/contract/nodedata.py
leap_model_parser/contract/ui_components.json
leap_model_parser/keras_json_model_import.py
leap_model_parser/leap_graph_editor.py
leap_model_parser/model_parser.py
leap_model_parser/utils/__init__.py
leap_model_parser/utils/layerpedia/__init__.py
leap_model_parser/utils/layerpedia/layerpedia.py
leap_model_parser/utils/tlinspection/__init__.py
leap_model_parser/utils/tlinspection/leapinspection.py
leap_model_parser/utils/uicomponents/__init__.py
leap_model_parser/utils/uicomponents/generatenodedata.py
leap_model_parser/utils/uicomponents/tensorflowinscpection.py
leap_model_parser/utils/uicomponents/ui_components.json
leap_model_parser/utils/uicomponents/ui_components_config.yaml
leap_model_parser-0.1.242.dist-info/LICENSE
leap_model_parser-0.1.242.dist-info/METADATA
leap_model_parser-0.1.242.dist-info/WHEEL
leap_model_parser-0.1.242.dist-info/entry_points.txt
leap_model_parser-0.1.242.dist-info/RECORD
