Metadata-Version: 2.3
Name: leap-model-parser
Version: 0.1.242
Summary: 
License: MIT
Author: idan
Author-email: idan.yogev@tensorleap.ai
Requires-Python: >=3.8,<3.11
Classifier: License :: OSI Approved :: MIT License
Classifier: Programming Language :: Python :: 3
Classifier: Programming Language :: Python :: 3.8
Classifier: Programming Language :: Python :: 3.9
Classifier: Programming Language :: Python :: 3.10
Requires-Dist: code-loader (>=1.0.127)
Requires-Dist: keras-data-format-converter (==0.1.24)
Requires-Dist: leap-model-rebuilder (==0.1.7)
Requires-Dist: numpy (>=1.22.3,<2.0.0)
Requires-Dist: onnx (==1.13.0)
Requires-Dist: onnx2kerastl (==0.0.186)
Requires-Dist: tensorflow (==2.12.0) ; platform_machine == "x86_64"
Requires-Dist: tensorflow-io-gcs-filesystem (==0.34.0)
Requires-Dist: tensorflow-macos (==2.12.0) ; platform_machine == "arm64"
Project-URL: Homepage, https://github.com/tensorleap/leap-model-parser
Project-URL: Repository, https://github.com/tensorleap/leap-model-parser
